{
  "project_info": {
    "project_number": "159589851717",
    "project_id": "xchange-chat",
    "storage_bucket": "xchange-chat.appspot.com"
  },
  "client": [
    {
      "client_info": {
        "mobilesdk_app_id": "1:159589851717:android:ad0ec139d20dd1d30b392c",
        "android_client_info": {
          "package_name": "com.sentura.xchange"
        }
      },
      "oauth_client": [
        {
          "client_id": "159589851717-g15afde67tso5mp2du6gesrbcc4h91ql.apps.googleusercontent.com",
          "client_type": 3
        }
      ],
      "api_key": [
        {
          "current_key": "AIzaSyA_X0k5AhlgenwWX6TjgOKJbHiPV88c4vE"
        }
      ],
      "services": {
        "appinvite_service": {
          "other_platform_oauth_client": [
            {
              "client_id": "159589851717-g15afde67tso5mp2du6gesrbcc4h91ql.apps.googleusercontent.com",
              "client_type": 3
            }
          ]
        }
      }
    }
  ],
  "configuration_version": "1"
}